{
	"info": {
		"_postman_id": "9d965d25-92da-4e15-9dc4-70cc4c409a40",
		"name": "Jobs RESTful API",
		"description": "# 🚀 Get started here\n\nThis collection guides you through CRUD operations (GET, POST, PUT, DELETE), variables, and tests.\n\n## 🔖 **How to use this collection**\n\n#### **Step 1: Send requests**\n\nRESTful APIs allow you to perform CRUD operations using the POST, GET, PUT, and DELETE HTTP methods.\n\nThis collection contains each of these request types. Open each request and click \"Send\" to see what happens.\n\n#### **Step 2: View responses**\n\nObserve the response tab for status code (200 OK), response time, and size.\n\n#### **Step 3: Send new Body data**\n\nUpdate or add new data in \"Body\" in the POST request. Typically, Body data is also used in PUT and PATCH requests.\n\n```\n{\n    \"name\": \"Add your name in the body\"\n}\n\n```\n\n#### **Step 4: Update the variable**\n\nVariables enable you to store and reuse values in Postman. We have created a variable called `base_url` with the sample request [https://postman-api-learner.glitch.me](https://postman-api-learner.glitch.me). Replace it with your API endpoint to customize this collection.\n\n#### **Step 5: Add tests in the \"Tests\" tab**\n\nTests help you confirm that your API is working as expected. You can write test scripts in JavaScript and view the output in the \"Test Results\" tab.\n\n<img src=\"https://content.pstmn.io/b5f280a7-4b09-48ec-857f-0a7ed99d7ef8/U2NyZWVuc2hvdCAyMDIzLTAzLTI3IGF0IDkuNDcuMjggUE0ucG5n\">\n\n## 💪 Pro tips\n\n- Use folders to group related requests and organize the collection.\n- Add more scripts in \"Tests\" to verify if the API works as expected and execute flows.\n    \n\n## ℹ️ Resources\n\n[Building requests](https://learning.postman.com/docs/sending-requests/requests/)  \n[Authorizing requests](https://learning.postman.com/docs/sending-requests/authorization/)  \n[Using variables](https://learning.postman.com/docs/sending-requests/variables/)  \n[Managing environments](https://learning.postman.com/docs/sending-requests/managing-environments/)  \n[Writing scripts](https://learning.postman.com/docs/writing-scripts/intro-to-scripts/)",
		"schema": "https://schema.getpostman.com/json/collection/v2.1.0/collection.json",
		"_exporter_id": "2284744"
	},
	"item": [
		{
			"name": "Auth",
			"item": [
				{
					"name": "Login",
					"event": [
						{
							"listen": "test",
							"script": {
								"exec": [
									"var res = pm.response.json();",
									"pm.environment.set('TOKEN', res.token);"
								],
								"type": "text/javascript",
								"packages": {}
							}
						}
					],
					"request": {
						"auth": {
							"type": "noauth"
						},
						"method": "POST",
						"header": [
							{
								"key": "Accept",
								"value": "application/json"
							},
							{
								"key": "Content-Type",
								"value": "application/json"
							}
						],
						"body": {
							"mode": "raw",
							"raw": "{\n    \"email\": \"admin@example.com\", //admin@example.com\n    \"password\": \"password\"\n}",
							"options": {
								"raw": {
									"language": "json"
								}
							}
						},
						"url": {
							"raw": "{{base_url}}/login",
							"host": [
								"{{base_url}}"
							],
							"path": [
								"login"
							]
						}
					},
					"response": []
				},
				{
					"name": "Logout",
					"event": [
						{
							"listen": "test",
							"script": {
								"exec": [
									"pm.environment.set('TOKEN', '');"
								],
								"type": "text/javascript"
							}
						}
					],
					"request": {
						"auth": {
							"type": "bearer",
							"bearer": [
								{
									"key": "token",
									"value": "{{Token}}",
									"type": "string"
								}
							]
						},
						"method": "POST",
						"header": [
							{
								"key": "Accept",
								"value": "application/json",
								"type": "text"
							},
							{
								"key": "Content-Type",
								"value": "application/json",
								"type": "text"
							}
						],
						"body": {
							"mode": "raw",
							"raw": "",
							"options": {
								"raw": {
									"language": "json"
								}
							}
						},
						"url": {
							"raw": "{{base_url}}/logout",
							"host": [
								"{{base_url}}"
							],
							"path": [
								"logout"
							]
						}
					},
					"response": []
				},
				{
					"name": "Register",
					"event": [
						{
							"listen": "test",
							"script": {
								"exec": [
									""
								],
								"type": "text/javascript",
								"packages": {}
							}
						},
						{
							"listen": "prerequest",
							"script": {
								"exec": [
									""
								],
								"type": "text/javascript",
								"packages": {}
							}
						}
					],
					"request": {
						"auth": {
							"type": "noauth"
						},
						"method": "POST",
						"header": [
							{
								"key": "Accept",
								"value": "application/json"
							}
						],
						"body": {
							"mode": "raw",
							"raw": "{\n\t\"name\": \"Add your name in the body\",\n    \"email\": \"new8@gmail.com\",\n    \"phone\": \"123456789\",\n    \"password\": \"password\",\n    \"password_confirmation\": \"password\",\n    \"role_id\": 2\n}",
							"options": {
								"raw": {
									"language": "json"
								}
							}
						},
						"url": {
							"raw": "{{base_url}}/register",
							"host": [
								"{{base_url}}"
							],
							"path": [
								"register"
							]
						},
						"description": "This is a POST request, submitting data to an API via the request body. This request submits JSON data, and the data is reflected in the response.\n\nA successful POST request typically returns a `200 OK` or `201 Created` response code."
					},
					"response": []
				},
				{
					"name": "Forgot Password",
					"event": [
						{
							"listen": "test",
							"script": {
								"exec": [
									""
								],
								"type": "text/javascript",
								"packages": {}
							}
						},
						{
							"listen": "prerequest",
							"script": {
								"exec": [
									""
								],
								"type": "text/javascript",
								"packages": {}
							}
						}
					],
					"request": {
						"auth": {
							"type": "noauth"
						},
						"method": "POST",
						"header": [
							{
								"key": "Accept",
								"value": "application/json"
							}
						],
						"body": {
							"mode": "raw",
							"raw": "{\n  \"email\": \"user@example.com\",\n  \"locale\": \"en\"\n}",
							"options": {
								"raw": {
									"language": "json"
								}
							}
						},
						"url": {
							"raw": "{{base_url}}/forgot-password",
							"host": [
								"{{base_url}}"
							],
							"path": [
								"forgot-password"
							]
						},
						"description": "This is a POST request, submitting data to an API via the request body. This request submits JSON data, and the data is reflected in the response.\n\nA successful POST request typically returns a `200 OK` or `201 Created` response code."
					},
					"response": []
				},
				{
					"name": "Reset Password",
					"event": [
						{
							"listen": "test",
							"script": {
								"exec": [
									""
								],
								"type": "text/javascript",
								"packages": {}
							}
						},
						{
							"listen": "prerequest",
							"script": {
								"exec": [
									""
								],
								"type": "text/javascript",
								"packages": {}
							}
						}
					],
					"request": {
						"auth": {
							"type": "noauth"
						},
						"method": "POST",
						"header": [
							{
								"key": "Accept",
								"value": "application/json"
							}
						],
						"body": {
							"mode": "raw",
							"raw": "{\n  \"email\": \"user@example.com\",\n  \"password\": \"password\",\n  \"password_confirmation\": \"password\",\n  \"token\": \"2wLDZpnmshkRMgtdn19AbiHVNXKEtIGH4sNcj9jVJlc2raUq0XfcCzZ2EKfq\"\n}\n",
							"options": {
								"raw": {
									"language": "json"
								}
							}
						},
						"url": {
							"raw": "{{base_url}}/reset-password",
							"host": [
								"{{base_url}}"
							],
							"path": [
								"reset-password"
							]
						},
						"description": "This is a POST request, submitting data to an API via the request body. This request submits JSON data, and the data is reflected in the response.\n\nA successful POST request typically returns a `200 OK` or `201 Created` response code."
					},
					"response": []
				},
				{
					"name": "Change Password",
					"event": [
						{
							"listen": "test",
							"script": {
								"exec": [
									""
								],
								"type": "text/javascript",
								"packages": {}
							}
						},
						{
							"listen": "prerequest",
							"script": {
								"exec": [
									""
								],
								"type": "text/javascript",
								"packages": {}
							}
						}
					],
					"request": {
						"auth": {
							"type": "bearer",
							"bearer": [
								{
									"key": "token",
									"value": "{{Token}}",
									"type": "string"
								}
							]
						},
						"method": "POST",
						"header": [
							{
								"key": "Accept",
								"value": "application/json"
							}
						],
						"body": {
							"mode": "raw",
							"raw": "{\n    \"current_password\":\"password\",\n    \"new_password\": \"password\",\n    \"new_password_confirmation\": \"password\"\n}",
							"options": {
								"raw": {
									"language": "json"
								}
							}
						},
						"url": {
							"raw": "{{base_url}}/users/change-password",
							"host": [
								"{{base_url}}"
							],
							"path": [
								"users",
								"change-password"
							]
						},
						"description": "This is a POST request, submitting data to an API via the request body. This request submits JSON data, and the data is reflected in the response.\n\nA successful POST request typically returns a `200 OK` or `201 Created` response code."
					},
					"response": []
				}
			]
		},
		{
			"name": "Users",
			"item": [
				{
					"name": "Get Users",
					"event": [
						{
							"listen": "test",
							"script": {
								"exec": [
									""
								],
								"type": "text/javascript"
							}
						}
					],
					"request": {
						"auth": {
							"type": "bearer",
							"bearer": [
								{
									"key": "token",
									"value": "{{Token}}",
									"type": "string"
								}
							]
						},
						"method": "GET",
						"header": [
							{
								"key": "Accept",
								"value": "application/json",
								"type": "text"
							},
							{
								"key": "Content-Type",
								"value": "application/json",
								"type": "text"
							}
						],
						"url": {
							"raw": "{{base_url}}/users",
							"host": [
								"{{base_url}}"
							],
							"path": [
								"users"
							]
						},
						"description": "This is a GET request and it is used to \"get\" data from an endpoint. There is no request body for a GET request, but you can use query parameters to help specify the resource you want data on (e.g., in this request, we have `id=1`).\n\nA successful GET response will have a `200 OK` status, and should include some kind of response body - for example, HTML web content or JSON data."
					},
					"response": []
				},
				{
					"name": "Show User",
					"event": [
						{
							"listen": "test",
							"script": {
								"exec": [
									""
								],
								"type": "text/javascript",
								"packages": {}
							}
						}
					],
					"request": {
						"auth": {
							"type": "bearer",
							"bearer": [
								{
									"key": "token",
									"value": "{{Token}}",
									"type": "string"
								}
							]
						},
						"method": "GET",
						"header": [
							{
								"key": "Accept",
								"value": "application/json"
							}
						],
						"url": {
							"raw": "{{base_url}}/users/me",
							"host": [
								"{{base_url}}"
							],
							"path": [
								"users",
								"me"
							]
						},
						"description": "This is a GET request and it is used to \"get\" data from an endpoint. There is no request body for a GET request, but you can use query parameters to help specify the resource you want data on (e.g., in this request, we have `id=1`).\n\nA successful GET response will have a `200 OK` status, and should include some kind of response body - for example, HTML web content or JSON data."
					},
					"response": []
				},
				{
					"name": "Show User Avatar",
					"event": [
						{
							"listen": "test",
							"script": {
								"exec": [
									""
								],
								"type": "text/javascript",
								"packages": {}
							}
						}
					],
					"request": {
						"auth": {
							"type": "bearer",
							"bearer": [
								{
									"key": "token",
									"value": "{{Token}}",
									"type": "string"
								}
							]
						},
						"method": "GET",
						"header": [
							{
								"key": "Accept",
								"value": "application/json"
							}
						],
						"url": {
							"raw": "{{base_url}}/users/1/avatar",
							"host": [
								"{{base_url}}"
							],
							"path": [
								"users",
								"1",
								"avatar"
							]
						},
						"description": "This is a GET request and it is used to \"get\" data from an endpoint. There is no request body for a GET request, but you can use query parameters to help specify the resource you want data on (e.g., in this request, we have `id=1`).\n\nA successful GET response will have a `200 OK` status, and should include some kind of response body - for example, HTML web content or JSON data."
					},
					"response": []
				},
				{
					"name": "Applied jobs",
					"event": [
						{
							"listen": "test",
							"script": {
								"exec": [
									""
								],
								"type": "text/javascript",
								"packages": {}
							}
						}
					],
					"request": {
						"auth": {
							"type": "bearer",
							"bearer": [
								{
									"key": "token",
									"value": "{{Token}}",
									"type": "string"
								}
							]
						},
						"method": "GET",
						"header": [
							{
								"key": "Accept",
								"value": "application/json"
							}
						],
						"url": {
							"raw": "{{base_url}}/users/jobs?page=1&per_page=20&sort=title&order=desc&q=vero",
							"host": [
								"{{base_url}}"
							],
							"path": [
								"users",
								"jobs"
							],
							"query": [
								{
									"key": "page",
									"value": "1"
								},
								{
									"key": "per_page",
									"value": "20"
								},
								{
									"key": "sort",
									"value": "title"
								},
								{
									"key": "order",
									"value": "desc"
								},
								{
									"key": "q",
									"value": "vero"
								}
							]
						},
						"description": "This is a GET request and it is used to \"get\" data from an endpoint. There is no request body for a GET request, but you can use query parameters to help specify the resource you want data on (e.g., in this request, we have `id=1`).\n\nA successful GET response will have a `200 OK` status, and should include some kind of response body - for example, HTML web content or JSON data."
					},
					"response": []
				},
				{
					"name": "Companies List",
					"event": [
						{
							"listen": "test",
							"script": {
								"exec": [
									""
								],
								"type": "text/javascript",
								"packages": {}
							}
						}
					],
					"request": {
						"auth": {
							"type": "bearer",
							"bearer": [
								{
									"key": "token",
									"value": "{{Token}}",
									"type": "string"
								}
							]
						},
						"method": "GET",
						"header": [
							{
								"key": "Accept",
								"value": "application/json"
							}
						],
						"url": {
							"raw": "{{base_url}}/users/companies?page=1&per_page=20&sort=title&order=desc&rating=1",
							"host": [
								"{{base_url}}"
							],
							"path": [
								"users",
								"companies"
							],
							"query": [
								{
									"key": "page",
									"value": "1"
								},
								{
									"key": "per_page",
									"value": "20"
								},
								{
									"key": "sort",
									"value": "title"
								},
								{
									"key": "order",
									"value": "desc"
								},
								{
									"key": "q",
									"value": "vero",
									"disabled": true
								},
								{
									"key": "rating",
									"value": "1"
								}
							]
						},
						"description": "This is a GET request and it is used to \"get\" data from an endpoint. There is no request body for a GET request, but you can use query parameters to help specify the resource you want data on (e.g., in this request, we have `id=1`).\n\nA successful GET response will have a `200 OK` status, and should include some kind of response body - for example, HTML web content or JSON data."
					},
					"response": []
				},
				{
					"name": "Add User Avatar",
					"event": [
						{
							"listen": "test",
							"script": {
								"exec": [
									""
								],
								"type": "text/javascript",
								"packages": {}
							}
						},
						{
							"listen": "prerequest",
							"script": {
								"exec": [
									""
								],
								"type": "text/javascript",
								"packages": {}
							}
						}
					],
					"request": {
						"auth": {
							"type": "bearer",
							"bearer": [
								{
									"key": "token",
									"value": "{{Token}}",
									"type": "string"
								}
							]
						},
						"method": "POST",
						"header": [
							{
								"key": "Accept",
								"value": "application/json"
							}
						],
						"body": {
							"mode": "formdata",
							"formdata": [
								{
									"key": "avatar",
									"type": "file",
									"src": "/Users/pejman/Downloads/images/profile.jpg"
								}
							]
						},
						"url": {
							"raw": "{{base_url}}/users/avatar",
							"host": [
								"{{base_url}}"
							],
							"path": [
								"users",
								"avatar"
							]
						},
						"description": "This is a POST request, submitting data to an API via the request body. This request submits JSON data, and the data is reflected in the response.\n\nA successful POST request typically returns a `200 OK` or `201 Created` response code."
					},
					"response": []
				},
				{
					"name": "Change User CV",
					"event": [
						{
							"listen": "test",
							"script": {
								"exec": [
									""
								],
								"type": "text/javascript",
								"packages": {}
							}
						},
						{
							"listen": "prerequest",
							"script": {
								"exec": [
									""
								],
								"type": "text/javascript",
								"packages": {}
							}
						}
					],
					"request": {
						"auth": {
							"type": "bearer",
							"bearer": [
								{
									"key": "token",
									"value": "{{Token}}",
									"type": "string"
								}
							]
						},
						"method": "POST",
						"header": [
							{
								"key": "Accept",
								"value": "application/json"
							}
						],
						"body": {
							"mode": "formdata",
							"formdata": [
								{
									"key": "cv",
									"type": "file",
									"src": "/Users/pejman/Desktop/Pejman's Resume.pdf"
								}
							]
						},
						"url": {
							"raw": "{{base_url}}/users/cv",
							"host": [
								"{{base_url}}"
							],
							"path": [
								"users",
								"cv"
							]
						},
						"description": "This is a POST request, submitting data to an API via the request body. This request submits JSON data, and the data is reflected in the response.\n\nA successful POST request typically returns a `200 OK` or `201 Created` response code."
					},
					"response": []
				},
				{
					"name": "Update User",
					"event": [
						{
							"listen": "test",
							"script": {
								"exec": [
									""
								],
								"type": "text/javascript",
								"packages": {}
							}
						}
					],
					"request": {
						"auth": {
							"type": "bearer",
							"bearer": [
								{
									"key": "token",
									"value": "{{Token}}",
									"type": "string"
								}
							]
						},
						"method": "PUT",
						"header": [
							{
								"key": "Accept",
								"value": "application/json"
							}
						],
						"body": {
							"mode": "raw",
							"raw": "{\n\t\"name\": \"Add your name in the body\",\n    \"phone\": \"111111111\"\n}",
							"options": {
								"raw": {
									"language": "json"
								}
							}
						},
						"url": {
							"raw": "{{base_url}}/users/",
							"host": [
								"{{base_url}}"
							],
							"path": [
								"users",
								""
							]
						},
						"description": "This is a PUT request and it is used to overwrite an existing piece of data. For instance, after you create an entity with a POST request, you may want to modify that later. You can do that using a PUT request. You typically identify the entity being updated by including an identifier in the URL (eg. `id=1`).\n\nA successful PUT request typically returns a `200 OK`, `201 Created`, or `204 No Content` response code."
					},
					"response": []
				},
				{
					"name": "Delete User",
					"event": [
						{
							"listen": "test",
							"script": {
								"exec": [
									"pm.test(\"Successful DELETE request\", function () {",
									"    pm.expect(pm.response.code).to.be.oneOf([200, 202, 204]);",
									"});",
									""
								],
								"type": "text/javascript"
							}
						}
					],
					"request": {
						"auth": {
							"type": "bearer",
							"bearer": [
								{
									"key": "token",
									"value": "{{Token}}",
									"type": "string"
								}
							]
						},
						"method": "DELETE",
						"header": [
							{
								"key": "Accept",
								"value": "application/json",
								"type": "text"
							}
						],
						"body": {
							"mode": "raw",
							"raw": "",
							"options": {
								"raw": {
									"language": "json"
								}
							}
						},
						"url": {
							"raw": "{{base_url}}/users/1",
							"host": [
								"{{base_url}}"
							],
							"path": [
								"users",
								"1"
							]
						},
						"description": "This is a DELETE request, and it is used to delete data that was previously created via a POST request. You typically identify the entity being updated by including an identifier in the URL (eg. `id=1`).\n\nA successful DELETE request typically returns a `200 OK`, `202 Accepted`, or `204 No Content` response code."
					},
					"response": []
				}
			]
		},
		{
			"name": "Jobs",
			"item": [
				{
					"name": "Get Jobs",
					"event": [
						{
							"listen": "test",
							"script": {
								"exec": [
									""
								],
								"type": "text/javascript",
								"packages": {}
							}
						}
					],
					"request": {
						"auth": {
							"type": "noauth"
						},
						"method": "GET",
						"header": [
							{
								"key": "Accept",
								"value": "application/json"
							},
							{
								"key": "Content-Type",
								"value": "application/json"
							}
						],
						"url": {
							"raw": "{{base_url}}/jobs?q=max&location=united",
							"host": [
								"{{base_url}}"
							],
							"path": [
								"jobs"
							],
							"query": [
								{
									"key": "q",
									"value": "max"
								},
								{
									"key": "location",
									"value": "united"
								}
							]
						},
						"description": "This is a GET request and it is used to \"get\" data from an endpoint. There is no request body for a GET request, but you can use query parameters to help specify the resource you want data on (e.g., in this request, we have `id=1`).\n\nA successful GET response will have a `200 OK` status, and should include some kind of response body - for example, HTML web content or JSON data."
					},
					"response": []
				},
				{
					"name": "Show Job",
					"event": [
						{
							"listen": "test",
							"script": {
								"exec": [
									""
								],
								"type": "text/javascript"
							}
						}
					],
					"request": {
						"method": "GET",
						"header": [
							{
								"key": "Accept",
								"value": "application/json",
								"type": "text"
							},
							{
								"key": "Content-Type",
								"value": "application/json",
								"type": "text"
							}
						],
						"url": {
							"raw": "{{base_url}}/jobs/1",
							"host": [
								"{{base_url}}"
							],
							"path": [
								"jobs",
								"1"
							]
						},
						"description": "This is a GET request and it is used to \"get\" data from an endpoint. There is no request body for a GET request, but you can use query parameters to help specify the resource you want data on (e.g., in this request, we have `id=1`).\n\nA successful GET response will have a `200 OK` status, and should include some kind of response body - for example, HTML web content or JSON data."
					},
					"response": []
				},
				{
					"name": "Add Job",
					"event": [
						{
							"listen": "test",
							"script": {
								"exec": [
									""
								],
								"type": "text/javascript"
							}
						}
					],
					"request": {
						"auth": {
							"type": "bearer",
							"bearer": [
								{
									"key": "token",
									"value": "{{Token}}",
									"type": "string"
								}
							]
						},
						"method": "POST",
						"header": [
							{
								"key": "Accept",
								"value": "application/json",
								"type": "text"
							},
							{
								"key": "Content-Type",
								"value": "application/json",
								"type": "text"
							}
						],
						"body": {
							"mode": "raw",
							"raw": "{\n\t\"title\": \"Job Title\",\n    \"description\": \"Job description\",\n    \"company_id\": 1,\n    \"tags\": [\"PHP\", \"MYSQL\"]\n}",
							"options": {
								"raw": {
									"language": "json"
								}
							}
						},
						"url": {
							"raw": "{{base_url}}/jobs",
							"host": [
								"{{base_url}}"
							],
							"path": [
								"jobs"
							]
						},
						"description": "This is a POST request, submitting data to an API via the request body. This request submits JSON data, and the data is reflected in the response.\n\nA successful POST request typically returns a `200 OK` or `201 Created` response code."
					},
					"response": []
				},
				{
					"name": "Apply Job",
					"event": [
						{
							"listen": "test",
							"script": {
								"exec": [
									""
								],
								"type": "text/javascript",
								"packages": {}
							}
						}
					],
					"request": {
						"auth": {
							"type": "bearer",
							"bearer": [
								{
									"key": "token",
									"value": "{{Token}}",
									"type": "string"
								}
							]
						},
						"method": "POST",
						"header": [
							{
								"key": "Accept",
								"value": "application/json"
							},
							{
								"key": "Content-Type",
								"value": "application/json"
							}
						],
						"body": {
							"mode": "raw",
							"raw": "{\n    \"message\": \"Apply cover letter description\"\n}",
							"options": {
								"raw": {
									"language": "json"
								}
							}
						},
						"url": {
							"raw": "{{base_url}}/jobs/2/apply",
							"host": [
								"{{base_url}}"
							],
							"path": [
								"jobs",
								"2",
								"apply"
							]
						},
						"description": "This is a POST request, submitting data to an API via the request body. This request submits JSON data, and the data is reflected in the response.\n\nA successful POST request typically returns a `200 OK` or `201 Created` response code."
					},
					"response": []
				},
				{
					"name": "Applicants",
					"event": [
						{
							"listen": "test",
							"script": {
								"exec": [
									""
								],
								"type": "text/javascript",
								"packages": {}
							}
						}
					],
					"protocolProfileBehavior": {
						"disableBodyPruning": true
					},
					"request": {
						"auth": {
							"type": "bearer",
							"bearer": [
								{
									"key": "token",
									"value": "{{Token}}",
									"type": "string"
								}
							]
						},
						"method": "GET",
						"header": [
							{
								"key": "Accept",
								"value": "application/json"
							},
							{
								"key": "Content-Type",
								"value": "application/json"
							}
						],
						"body": {
							"mode": "raw",
							"raw": "",
							"options": {
								"raw": {
									"language": "json"
								}
							}
						},
						"url": {
							"raw": "{{base_url}}/jobs/8/applicants",
							"host": [
								"{{base_url}}"
							],
							"path": [
								"jobs",
								"8",
								"applicants"
							]
						},
						"description": "This is a POST request, submitting data to an API via the request body. This request submits JSON data, and the data is reflected in the response.\n\nA successful POST request typically returns a `200 OK` or `201 Created` response code."
					},
					"response": []
				},
				{
					"name": "Update Job",
					"event": [
						{
							"listen": "test",
							"script": {
								"exec": [
									"pm.test(\"Successful PUT request\", function () {",
									"    pm.expect(pm.response.code).to.be.oneOf([200, 201, 204]);",
									"});",
									""
								],
								"type": "text/javascript"
							}
						}
					],
					"request": {
						"auth": {
							"type": "bearer",
							"bearer": [
								{
									"key": "token",
									"value": "{{Token}}",
									"type": "string"
								}
							]
						},
						"method": "PUT",
						"header": [],
						"body": {
							"mode": "raw",
							"raw": "{\n\t\"title\": \"Job Title2\",\n    \"description\": \"Job description1\",\n    \"tags\": [\"Vue.js\", \"Nuxt.js\"]\n}",
							"options": {
								"raw": {
									"language": "json"
								}
							}
						},
						"url": {
							"raw": "{{base_url}}/jobs/34",
							"host": [
								"{{base_url}}"
							],
							"path": [
								"jobs",
								"34"
							]
						},
						"description": "This is a PUT request and it is used to overwrite an existing piece of data. For instance, after you create an entity with a POST request, you may want to modify that later. You can do that using a PUT request. You typically identify the entity being updated by including an identifier in the URL (eg. `id=1`).\n\nA successful PUT request typically returns a `200 OK`, `201 Created`, or `204 No Content` response code."
					},
					"response": []
				},
				{
					"name": "Delete Job",
					"event": [
						{
							"listen": "test",
							"script": {
								"exec": [
									""
								],
								"type": "text/javascript"
							}
						}
					],
					"request": {
						"auth": {
							"type": "bearer",
							"bearer": [
								{
									"key": "token",
									"value": "{{Token}}",
									"type": "string"
								}
							]
						},
						"method": "DELETE",
						"header": [
							{
								"key": "Accept",
								"value": "application/json",
								"type": "text"
							}
						],
						"body": {
							"mode": "raw",
							"raw": "",
							"options": {
								"raw": {
									"language": "json"
								}
							}
						},
						"url": {
							"raw": "{{base_url}}/jobs/42",
							"host": [
								"{{base_url}}"
							],
							"path": [
								"jobs",
								"42"
							]
						},
						"description": "This is a DELETE request, and it is used to delete data that was previously created via a POST request. You typically identify the entity being updated by including an identifier in the URL (eg. `id=1`).\n\nA successful DELETE request typically returns a `200 OK`, `202 Accepted`, or `204 No Content` response code."
					},
					"response": []
				},
				{
					"name": "Get Jobs By Tag",
					"event": [
						{
							"listen": "test",
							"script": {
								"exec": [
									""
								],
								"type": "text/javascript"
							}
						}
					],
					"request": {
						"method": "GET",
						"header": [
							{
								"key": "Accept",
								"value": "application/json",
								"type": "text"
							},
							{
								"key": "",
								"value": "",
								"type": "text"
							}
						],
						"url": {
							"raw": "{{base_url}}/jobs/tags/1",
							"host": [
								"{{base_url}}"
							],
							"path": [
								"jobs",
								"tags",
								"1"
							]
						},
						"description": "This is a GET request and it is used to \"get\" data from an endpoint. There is no request body for a GET request, but you can use query parameters to help specify the resource you want data on (e.g., in this request, we have `id=1`).\n\nA successful GET response will have a `200 OK` status, and should include some kind of response body - for example, HTML web content or JSON data."
					},
					"response": []
				}
			]
		},
		{
			"name": "Companies",
			"item": [
				{
					"name": "Get Companies",
					"event": [
						{
							"listen": "test",
							"script": {
								"exec": [
									""
								],
								"type": "text/javascript"
							}
						}
					],
					"request": {
						"method": "GET",
						"header": [
							{
								"key": "Accept",
								"value": "application/json",
								"type": "text"
							},
							{
								"key": "Content-Type",
								"value": "application/json",
								"type": "text"
							}
						],
						"url": {
							"raw": "{{base_url}}/companies",
							"host": [
								"{{base_url}}"
							],
							"path": [
								"companies"
							]
						},
						"description": "This is a GET request and it is used to \"get\" data from an endpoint. There is no request body for a GET request, but you can use query parameters to help specify the resource you want data on (e.g., in this request, we have `id=1`).\n\nA successful GET response will have a `200 OK` status, and should include some kind of response body - for example, HTML web content or JSON data."
					},
					"response": []
				},
				{
					"name": "Show Companies",
					"event": [
						{
							"listen": "test",
							"script": {
								"exec": [
									""
								],
								"type": "text/javascript"
							}
						}
					],
					"request": {
						"method": "GET",
						"header": [
							{
								"key": "Accept",
								"value": "application/json",
								"type": "text"
							},
							{
								"key": "Content-Type",
								"value": "application/json",
								"type": "text"
							}
						],
						"url": {
							"raw": "{{base_url}}/companies/2",
							"host": [
								"{{base_url}}"
							],
							"path": [
								"companies",
								"2"
							]
						},
						"description": "This is a GET request and it is used to \"get\" data from an endpoint. There is no request body for a GET request, but you can use query parameters to help specify the resource you want data on (e.g., in this request, we have `id=1`).\n\nA successful GET response will have a `200 OK` status, and should include some kind of response body - for example, HTML web content or JSON data."
					},
					"response": []
				},
				{
					"name": "Add Companies",
					"event": [
						{
							"listen": "test",
							"script": {
								"exec": [
									""
								],
								"type": "text/javascript"
							}
						}
					],
					"request": {
						"auth": {
							"type": "bearer",
							"bearer": [
								{
									"key": "token",
									"value": "{{Token}}",
									"type": "string"
								}
							]
						},
						"method": "POST",
						"header": [
							{
								"key": "Accept",
								"value": "application/json",
								"type": "text"
							},
							{
								"key": "Content-Type",
								"value": "application/json",
								"type": "text"
							}
						],
						"body": {
							"mode": "raw",
							"raw": "{\n\t\"title\": \"Job Title\",\n    \"description\": \"Job description\",\n    \"rating\": 5,\n    \"website\": \"http://job.com\",\n    \"employes\": 20\n}",
							"options": {
								"raw": {
									"language": "json"
								}
							}
						},
						"url": {
							"raw": "{{base_url}}/companies",
							"host": [
								"{{base_url}}"
							],
							"path": [
								"companies"
							]
						},
						"description": "This is a POST request, submitting data to an API via the request body. This request submits JSON data, and the data is reflected in the response.\n\nA successful POST request typically returns a `200 OK` or `201 Created` response code."
					},
					"response": []
				},
				{
					"name": "Add Companies Images",
					"event": [
						{
							"listen": "test",
							"script": {
								"exec": [
									""
								],
								"type": "text/javascript"
							}
						}
					],
					"request": {
						"auth": {
							"type": "bearer",
							"bearer": [
								{
									"key": "token",
									"value": "{{Token}}",
									"type": "string"
								}
							]
						},
						"method": "POST",
						"header": [
							{
								"key": "Accept",
								"value": "application/json",
								"type": "text"
							},
							{
								"key": "Content-Type",
								"value": "multipart/form-data",
								"type": "text"
							},
							{
								"key": "",
								"value": "",
								"type": "text",
								"disabled": true
							}
						],
						"body": {
							"mode": "formdata",
							"formdata": [
								{
									"key": "images[]",
									"type": "file",
									"src": "/Users/pejman/Documents/screenshots/Screenshot 2024-05-23 at 18.55.29.png"
								},
								{
									"key": "images[]",
									"type": "file",
									"src": "/Users/pejman/Documents/screenshots/Screenshot 2024-05-23 at 18.55.29.png"
								},
								{
									"key": "image",
									"type": "file",
									"src": [],
									"disabled": true
								}
							]
						},
						"url": {
							"raw": "{{base_url}}/companies/1/images/",
							"host": [
								"{{base_url}}"
							],
							"path": [
								"companies",
								"1",
								"images",
								""
							]
						},
						"description": "This is a POST request, submitting data to an API via the request body. This request submits JSON data, and the data is reflected in the response.\n\nA successful POST request typically returns a `200 OK` or `201 Created` response code."
					},
					"response": []
				},
				{
					"name": "Add Companies Logo",
					"event": [
						{
							"listen": "test",
							"script": {
								"exec": [
									""
								],
								"type": "text/javascript",
								"packages": {}
							}
						}
					],
					"request": {
						"auth": {
							"type": "bearer",
							"bearer": [
								{
									"key": "token",
									"value": "{{Token}}",
									"type": "string"
								}
							]
						},
						"method": "POST",
						"header": [
							{
								"key": "Accept",
								"value": "application/json"
							},
							{
								"key": "Content-Type",
								"value": "multipart/form-data"
							},
							{
								"key": "",
								"value": "",
								"disabled": true
							}
						],
						"body": {
							"mode": "formdata",
							"formdata": [
								{
									"key": "logo",
									"type": "file",
									"src": "/Users/pejman/Downloads/images/599-800x800.jpeg"
								}
							]
						},
						"url": {
							"raw": "{{base_url}}/companies/2/logo/",
							"host": [
								"{{base_url}}"
							],
							"path": [
								"companies",
								"2",
								"logo",
								""
							]
						},
						"description": "This is a POST request, submitting data to an API via the request body. This request submits JSON data, and the data is reflected in the response.\n\nA successful POST request typically returns a `200 OK` or `201 Created` response code."
					},
					"response": []
				},
				{
					"name": "Delete Companies Image",
					"event": [
						{
							"listen": "test",
							"script": {
								"exec": [
									""
								],
								"type": "text/javascript"
							}
						}
					],
					"request": {
						"auth": {
							"type": "bearer",
							"bearer": [
								{
									"key": "token",
									"value": "{{Token}}",
									"type": "string"
								}
							]
						},
						"method": "DELETE",
						"header": [
							{
								"key": "Accept",
								"value": "application/json",
								"type": "text"
							},
							{
								"key": "Content-Type",
								"value": "multipart/form-data",
								"type": "text"
							},
							{
								"key": "",
								"value": "",
								"type": "text",
								"disabled": true
							}
						],
						"body": {
							"mode": "formdata",
							"formdata": []
						},
						"url": {
							"raw": "{{base_url}}/companies/image/1",
							"host": [
								"{{base_url}}"
							],
							"path": [
								"companies",
								"image",
								"1"
							]
						},
						"description": "This is a POST request, submitting data to an API via the request body. This request submits JSON data, and the data is reflected in the response.\n\nA successful POST request typically returns a `200 OK` or `201 Created` response code."
					},
					"response": []
				},
				{
					"name": "Update Companies",
					"event": [
						{
							"listen": "test",
							"script": {
								"exec": [
									"pm.test(\"Successful PUT request\", function () {",
									"    pm.expect(pm.response.code).to.be.oneOf([200, 201, 204]);",
									"});",
									""
								],
								"type": "text/javascript"
							}
						}
					],
					"request": {
						"auth": {
							"type": "bearer",
							"bearer": [
								{
									"key": "token",
									"value": "{{Token}}",
									"type": "string"
								}
							]
						},
						"method": "PUT",
						"header": [
							{
								"key": "Accept",
								"value": "application/json",
								"type": "text"
							}
						],
						"body": {
							"mode": "raw",
							"raw": "{\n\t\"title\": \"Job Title1\",\n    \"description\": \"Job description1\",\n    \"rating\": 5,\n    \"website\": \"http://job.com1\",\n    \"employes\": 201\n}",
							"options": {
								"raw": {
									"language": "json"
								}
							}
						},
						"url": {
							"raw": "{{base_url}}/companies/1",
							"host": [
								"{{base_url}}"
							],
							"path": [
								"companies",
								"1"
							]
						},
						"description": "This is a PUT request and it is used to overwrite an existing piece of data. For instance, after you create an entity with a POST request, you may want to modify that later. You can do that using a PUT request. You typically identify the entity being updated by including an identifier in the URL (eg. `id=1`).\n\nA successful PUT request typically returns a `200 OK`, `201 Created`, or `204 No Content` response code."
					},
					"response": []
				},
				{
					"name": "Delete Companies",
					"event": [
						{
							"listen": "test",
							"script": {
								"exec": [
									""
								],
								"type": "text/javascript"
							}
						}
					],
					"request": {
						"auth": {
							"type": "bearer",
							"bearer": [
								{
									"key": "token",
									"value": "{{Token}}",
									"type": "string"
								}
							]
						},
						"method": "DELETE",
						"header": [
							{
								"key": "Accept",
								"value": "application/json",
								"type": "text"
							}
						],
						"body": {
							"mode": "raw",
							"raw": "",
							"options": {
								"raw": {
									"language": "json"
								}
							}
						},
						"url": {
							"raw": "{{base_url}}/companies/20",
							"host": [
								"{{base_url}}"
							],
							"path": [
								"companies",
								"20"
							]
						},
						"description": "This is a DELETE request, and it is used to delete data that was previously created via a POST request. You typically identify the entity being updated by including an identifier in the URL (eg. `id=1`).\n\nA successful DELETE request typically returns a `200 OK`, `202 Accepted`, or `204 No Content` response code."
					},
					"response": []
				},
				{
					"name": "Get Companies By Tag",
					"event": [
						{
							"listen": "test",
							"script": {
								"exec": [
									""
								],
								"type": "text/javascript"
							}
						}
					],
					"request": {
						"method": "GET",
						"header": [
							{
								"key": "Accept",
								"value": "application/json",
								"type": "text"
							},
							{
								"key": "",
								"value": "",
								"type": "text"
							}
						],
						"url": {
							"raw": "{{base_url}}/companies/tags/1",
							"host": [
								"{{base_url}}"
							],
							"path": [
								"companies",
								"tags",
								"1"
							]
						},
						"description": "This is a GET request and it is used to \"get\" data from an endpoint. There is no request body for a GET request, but you can use query parameters to help specify the resource you want data on (e.g., in this request, we have `id=1`).\n\nA successful GET response will have a `200 OK` status, and should include some kind of response body - for example, HTML web content or JSON data."
					},
					"response": []
				}
			]
		},
		{
			"name": "Search",
			"item": [
				{
					"name": "Jobs",
					"event": [
						{
							"listen": "test",
							"script": {
								"exec": [
									""
								],
								"type": "text/javascript",
								"packages": {}
							}
						}
					],
					"request": {
						"auth": {
							"type": "bearer",
							"bearer": [
								{
									"key": "token",
									"value": "{{Token}}",
									"type": "string"
								}
							]
						},
						"method": "GET",
						"header": [
							{
								"key": "Accept",
								"value": "application/json"
							},
							{
								"key": "Content-Type",
								"value": "application/json"
							}
						],
						"url": {
							"raw": "{{base_url}}/search/jobs?q=nihil",
							"host": [
								"{{base_url}}"
							],
							"path": [
								"search",
								"jobs"
							],
							"query": [
								{
									"key": "q",
									"value": "nihil"
								}
							]
						},
						"description": "This is a GET request and it is used to \"get\" data from an endpoint. There is no request body for a GET request, but you can use query parameters to help specify the resource you want data on (e.g., in this request, we have `id=1`).\n\nA successful GET response will have a `200 OK` status, and should include some kind of response body - for example, HTML web content or JSON data."
					},
					"response": []
				},
				{
					"name": "Locations",
					"event": [
						{
							"listen": "test",
							"script": {
								"exec": [
									""
								],
								"type": "text/javascript",
								"packages": {}
							}
						}
					],
					"request": {
						"auth": {
							"type": "bearer",
							"bearer": [
								{
									"key": "token",
									"value": "{{Token}}",
									"type": "string"
								}
							]
						},
						"method": "GET",
						"header": [
							{
								"key": "Accept",
								"value": "application/json"
							},
							{
								"key": "Content-Type",
								"value": "application/json"
							}
						],
						"url": {
							"raw": "{{base_url}}/search/locations?q=us",
							"host": [
								"{{base_url}}"
							],
							"path": [
								"search",
								"locations"
							],
							"query": [
								{
									"key": "q",
									"value": "us"
								}
							]
						},
						"description": "This is a GET request and it is used to \"get\" data from an endpoint. There is no request body for a GET request, but you can use query parameters to help specify the resource you want data on (e.g., in this request, we have `id=1`).\n\nA successful GET response will have a `200 OK` status, and should include some kind of response body - for example, HTML web content or JSON data."
					},
					"response": []
				}
			]
		}
	],
	"event": [
		{
			"listen": "prerequest",
			"script": {
				"type": "text/javascript",
				"exec": [
					""
				]
			}
		},
		{
			"listen": "test",
			"script": {
				"type": "text/javascript",
				"exec": [
					""
				]
			}
		}
	],
	"variable": [
		{
			"key": "id",
			"value": "1"
		},
		{
			"key": "base_url",
			"value": "https://postman-rest-api-learner.glitch.me/"
		}
	]
}